{
  "_key": "!items!24205a5d197e7043",
  "_id": "24205a5d197e7043",
  "name": "Awakened Mind",
  "type": "feat",
  "effects": [],
  "system": {
    "activities": {},
    "uses": {
      "spent": 0,
      "max": "",
      "recovery": []
    },
    "description": {
      "value": "<div class=\"ariadne-entry\"><p><strong>Source:</strong> Ariadne's Book of Legends - Alpha v1.2, p. 92.</p><p>Tier I: Awakened Mind</p><p>Expanded Intellect. Your Intelligence score increases by 2, as does your Intelligence score maximum.</p><p>Psychic Deflection. When you take psychic damage, you can use your reaction to nullify it. Optionally, you can redirect it toward a creature you can see within 60 feet. It must succeed on an Intelligence saving throw against a DC equal to 8 + your Intelligence modifier + your proficiency bonus or take the full instance damage in your stead.</p><p>Telekinetic. You are always under the effects of the Telekinesis spell. Intelligence is your spellcasting ability for resolving contests against creatures you target with your telekinetic grip. The range of your telekinesis is 120 feet rather than 60 feet, and you can target up to two creatures or objects simultaneously.</p></div>",
      "chat": ""
    },
    "identifier": "awakened-mind",
    "source": {
      "book": "Ariadne's Book of Legends",
      "page": "92",
      "license": "",
      "custom": "Original en-US text from Alpha v1.2",
      "rules": "2014",
      "revision": 1
    },
    "advancement": {},
    "crewed": false,
    "enchant": {},
    "prerequisites": {
      "level": null,
      "repeatable": false,
      "items": []
    },
    "properties": [],
    "requirements": "Heroic Path: Legendary Psion",
    "type": {
      "value": "feat",
      "subtype": ""
    }
  },
  "flags": {
    "ariadne": {
      "version": "Alpha v1.2",
      "category": "heroic-path-stage",
      "sourcePage": "92",
      "language": "en-US",
      "originalText": true,
      "automation": "reference",
      "heroicPath": "Legendary Psion",
      "stageType": "Tier I",
      "stageOrder": 1
    }
  },
  "img": "systems/dnd5e/icons/svg/items/feature.svg",
  "folder": null,
  "sort": 100000,
  "_stats": {
    "compendiumSource": null,
    "duplicateSource": null,
    "exportSource": null,
    "coreVersion": "14.361",
    "systemId": "dnd5e",
    "systemVersion": "5.3.3",
    "createdTime": 1783771200000,
    "modifiedTime": 1783771200000,
    "lastModifiedBy": null
  },
  "ownership": {
    "default": 0
  }
}