{
  "_key": "!items!461150d54a64ddef",
  "_id": "461150d54a64ddef",
  "name": "Untouchable",
  "type": "feat",
  "effects": [],
  "system": {
    "activities": {},
    "uses": {
      "spent": 0,
      "max": "",
      "recovery": []
    },
    "description": {
      "value": "<div class=\"ariadne-entry\"><p><strong>Source:</strong> Ariadne's Book of Legends - Alpha v1.2, p. 62-65.</p><p>Untouchable</p><p>Starting at 22nd level, you have become so proficient at avoiding strikes that hitting you is considered a feat of legend. Whenever you use your Uncanny Dodge feature, instead of halving the damage, you make an attack that would hit you miss instead.</p></div>",
      "chat": ""
    },
    "identifier": "rogue-untouchable",
    "source": {
      "book": "Ariadne's Book of Legends",
      "page": "62-65",
      "license": "",
      "custom": "Original en-US text from Alpha v1.2",
      "rules": "2014",
      "revision": 1
    },
    "advancement": {},
    "crewed": false,
    "enchant": {},
    "prerequisites": {
      "level": 20,
      "repeatable": false,
      "items": []
    },
    "properties": [],
    "requirements": "Rogue level 22",
    "type": {
      "value": "class",
      "subtype": ""
    }
  },
  "flags": {
    "ariadne": {
      "version": "Alpha v1.2",
      "category": "legendary-class-feature",
      "sourcePage": "62-65",
      "language": "en-US",
      "originalText": true,
      "automation": "reference",
      "class": "Rogue",
      "legendaryLevel": 22,
      "originalFeatureName": "Untouchable",
      "granularity": "individual-feature"
    }
  },
  "img": "systems/dnd5e/icons/svg/items/feature.svg",
  "folder": null,
  "sort": 100000,
  "_stats": {
    "compendiumSource": null,
    "duplicateSource": null,
    "exportSource": null,
    "coreVersion": "14.361",
    "systemId": "dnd5e",
    "systemVersion": "5.3.3",
    "createdTime": 1783771200000,
    "modifiedTime": 1783771200000,
    "lastModifiedBy": null
  },
  "ownership": {
    "default": 0
  }
}